sphinxcontrib_jsonschema-0.9.3-py3.6-nspkg.pth
sphinxcontrib/jsonschema.py
sphinxcontrib_jsonschema-0.9.3.dist-info/DESCRIPTION.rst
sphinxcontrib_jsonschema-0.9.3.dist-info/METADATA
sphinxcontrib_jsonschema-0.9.3.dist-info/RECORD
sphinxcontrib_jsonschema-0.9.3.dist-info/WHEEL
sphinxcontrib_jsonschema-0.9.3.dist-info/metadata.json
sphinxcontrib_jsonschema-0.9.3.dist-info/namespace_packages.txt
sphinxcontrib_jsonschema-0.9.3.dist-info/top_level.txt
